{
  "nodelang":{
    "en:base.start":{
      "text":"Start"
    },
    "en:base.console.log":{
      "text":"Console.Log"
    },
    "en:base.if":{
      "text":"If"
    }
  },
  "portlang":{
    "en:base.console.log.text":{
      "text":"Text"
    }
  }
  "nodes":[
    {
      "id":"start",
      "lang":"node.base.start",
      "type":"event",
      "inputs":[],
      "outputs":[
        {
          "id":"flow_out",
          "type":"flow"
        }
      ],
      "event":{
        "id":"init"
      }
    },
    {
      "id":"console.log",
      "lang":"node.base.console.log",
      "type":"node",
      "inputs":[
        {
          "id":"flow_in",
          "type":"flow",
          "lang":"port.base.console.log.text"
        }
        {
          "id":"text",
          "type":"string"
        }
      ],
      "outputs":[
        {
          "id":"flow_out",
          "type":"flow"
        }
      ]
    }
    {
      "id":"if",
      "lang":"node.base.if",
      "type":"node",
      "inputs":[
        {
          "id":"flow_in",
          "type":"flow"
        }
        {
          "id":"condition",
          "type":"bool"
        }
      ],
      "outputs":[
        {
          "id":"true",
          "type":"flow"
        }
        {
          "id":"false",
          "type":"flow"
        }
      ]
    }
  ]
}
